zsx_HMM.py
zsx_HMM-2.0.0.dist-info/METADATA
zsx_HMM-2.0.0.dist-info/WHEEL
zsx_HMM-2.0.0.dist-info/top_level.txt
zsx_HMM-2.0.0.dist-info/RECORD
